{
  "potentialAction": "",
  "identifier": "",
  "sameAs": "",
  "url": "",
  "image": "Greek Wrap",
  "alternateName": "",
  "name": "",
  "description": "",
  "mainEntityOfPage": "",
  "disambiguatingDescription": "",
  "subjectOf": "",
  "additionalType": "Recipe",
  "engage": {
    "CreativeWork": {
      "typicalAgeRange": "",
      "hasPart": "",
      "sdDatePublished": "",
      "educationalLevel": "",
      "releasedEvent": "",
      "schemaVersion": "",
      "contentLocation": "",
      "locationCreated": "",
      "aggregateRating": "",
      "temporalCoverage": "",
      "accessModeSufficient": "",
      "accountablePerson": "",
      "mainEntity": "",
      "sdPublisher": "",
      "spatialCoverage": "",
      "reviews": "",
      "exampleOfWork": "",
      "maintainer": "",
      "editor": "",
      "offers": "",
      "discussionUrl": "",
      "award": "",
      "sdLicense": "",
      "copyrightHolder": "",
      "accessibilityHazard": "",
      "copyrightYear": 0,
      "awards": "",
      "publisherImprint": "",
      "commentCount": "",
      "spatial": "",
      "recordedAt": "",
      "abstract": "",
      "fileFormat": "",
      "isPartOf": "",
      "temporal": "",
      "accessibilitySummary": "",
      "inLanguage": "",
      "educationalAlignment": "",
      "associatedMedia": "",
      "funder": "",
      "position": "",
      "audio": "",
      "workExample": "",
      "encoding": "",
      "interactivityType": "",
      "provider": "",
      "character": "",
      "sourceOrganization": "",
      "audience": "",
      "materialExtent": "",
      "video": "",
      "accessibilityFeature": "",
      "publisher": "",
      "text": "",
      "publication": "",
      "contributor": "",
      "encodingFormat": "",
      "review": "",
      "accessibilityControl": "",
      "license": "",
      "sponsor": "",
      "encodings": "",
      "about": "",
      "isBasedOn": "",
      "creator": "",
      "publishingPrinciples": "",
      "producer": "",
      "correction": "",
      "workTranslation": "",
      "mentions": "",
      "contentReferenceTime": "",
      "dateCreated": "",
      "educationalUse": "",
      "teaches": "",
      "alternativeHeadline": "",
      "datePublished": "",
      "isAccessibleForFree": 0,
      "headline": "",
      "translationOfWork": "",
      "acquireLicensePage": "",
      "conditionsOfAccess": "",
      "citation": "",
      "accessibilityAPI": "",
      "interactionStatistic": "",
      "contentRating": "",
      "accessMode": "",
      "material": "",
      "isFamilyFriendly": 0,
      "assesses": "",
      "keywords": "",
      "version": "",
      "dateModified": "",
      "learningResourceType": "",
      "genre": "",
      "creativeWorkStatus": "",
      "pattern": "",
      "editEIDR": "",
      "author": "",
      "size": "",
      "translator": "",
      "timeRequired": "",
      "usageInfo": "",
      "isBasedOnUrl": "",
      "thumbnailUrl": "",
      "expires": "",
      "comment": ""
    },
    "HowTo": {
      "steps": [
        "Fry/BBQ a Wrap",
        "Paste Garlic Butter",
        "Add Sliced Tomatoes",
        "Add Sliced Peppers",
        "Season",
        "Wait for wrap to get toasty",
        "Fold into packet and eat"
      ],
      "step": "",
      "supply": "",
      "tool": "",
      "prepTime": "0:00",
      "yield": "",
      "performTime": "3:00",
      "estimatedCost": "",
      "totalTime": ""
    },
    "Recipe": {
      "recipeIngredient": [
        "Wrap",
        "Large Tomatoes",
        "Peppers",
        "Olive Oil",
        "Seasoning"
      ],
      "recipeInstructions": "",
      "ingredients": "",
      "recipeYield": "",
      "recipeCategory": "",
      "cookingMethod": "",
      "suitableForDiet": "",
      "nutrition": "",
      "recipeCuisine": "",
      "cookTime": ""
    }
  }
}
